{
  "DalamudPluginUpdateSuccessful": {
    "message": "    》 {0} обновлено до v{1}.",
    "description": "Locs.DalamudPluginUpdateSuccessful"
  },
  "DalamudPluginUpdateFailed": {
    "message": "    》 {0} обновление до v{1} не удалось.",
    "description": "Locs.DalamudPluginUpdateFailed"
  },
  "DalamudUnloadHelp": {
    "message": "Выгружает внутриигровое дополнение XIVLauncher.",
    "description": "DalamudCommands.SetupCommands"
  },
  "DalamudPluginReloadHelp": {
    "message": "Перезагружает все плагины.",
    "description": "DalamudCommands.SetupCommands"
  },
  "DalamudCmdInfoHelp": {
    "message": "Показывает список доступных команд.",
    "description": "DalamudCommands.SetupCommands"
  },
  "DalamudMuteHelp": {
    "message": "Запретить слово или предложение при появления в чате. Использование: /xlmute <word or sentence>",
    "description": "DalamudCommands.SetupCommands"
  },
  "DalamudMuteListHelp": {
    "message": "Список запрещенных слов или предложений.",
    "description": "DalamudCommands.SetupCommands"
  },
  "DalamudUnmuteHelp": {
    "message": "Разрешить слово или предложение. Использование: /xlunmute <word or sentence>",
    "description": "DalamudCommands.SetupCommands"
  },
  "DalamudLastLinkHelp": {
    "message": "Открыть последнюю опубликованную ссылку в браузере по умолчанию.",
    "description": "DalamudCommands.SetupCommands"
  },
  "DalamudBgmSetHelp": {
    "message": "Установить фоновую музыку в игре. Использование: /xlbgmset <BGM ID>",
    "description": "DalamudCommands.SetupCommands"
  },
  "DalamudDevMenuHelp": {
    "message": "Вывести отладку меню разработчиков",
    "description": "DalamudCommands.SetupCommands"
  },
  "DalamudDevDataMenuHelp": {
    "message": "Вывести DEBUG меню данных разработчика. Использование: /xldata [Тип раскрывающегося списка данных]",
    "description": "DalamudCommands.SetupCommands"
  },
  "DalamudIMEPanelHelp": {
    "message": "Draw IME panel",
    "description": "DalamudCommands.SetupCommands"
  },
  "DalamudDevLogHelp": {
    "message": "Открыть DEBUG журнал разработчика",
    "description": "DalamudCommands.SetupCommands"
  },
  "DalamudInstallerHelp": {
    "message": "Открыть установщик плагинов",
    "description": "DalamudCommands.SetupCommands"
  },
  "DalamudCreditsHelp": {
    "message": "Открывает титры для dalamud.",
    "description": "DalamudCommands.SetupCommands"
  },
  "DalamudLanguageHelp": {
    "message": "Установите язык для внутриигровых дополнений и плагинов, которые это поддерживают. Доступные языки: ",
    "description": "DalamudCommands.SetupCommands"
  },
  "DalamudSettingsHelp": {
    "message": "Измените различные настройки внутриигровых дополнений, такие как каналы чата и настройка бота Discord.",
    "description": "DalamudCommands.SetupCommands"
  },
  "DalamudCmdHelpAvailable": {
    "message": "Доступные команды:",
    "description": "DalamudCommands.OnHelpCommand"
  },
  "DalamudMuteNoArgs": {
    "message": "Пожалуйста, предоставьте слово для запрета.",
    "description": "DalamudCommands.OnBadWordsAddCommand"
  },
  "DalamudMuted": {
    "message": "Запрещено \"{0}\".",
    "description": "DalamudCommands.OnBadWordsAddCommand"
  },
  "DalamudNoneMuted": {
    "message": "Нет запрещенных слов или предложений.",
    "description": "DalamudCommands.OnBadWordsListCommand"
  },
  "DalamudUnmuted": {
    "message": "Удалено из запрещенных слов \"{0}\".",
    "description": "DalamudCommands.OnBadWordsRemoveCommand"
  },
  "DalamudNoLastLink": {
    "message": "Нет последней ссылки...",
    "description": "DalamudCommands.OnLastLinkCommand"
  },
  "DalamudOpeningLink": {
    "message": "Открытие {0}",
    "description": "DalamudCommands.OnLastLinkCommand"
  },
  "DalamudLanguageSetTo": {
    "message": "Установлен язык: {0}",
    "description": "DalamudCommands.OnSetLanguageCommand"
  },
  "InstallerDevTools": {
    "message": "Dev Tools",
    "description": "Locs.get_Group_DevTools"
  },
  "InstallerInstalledPlugins": {
    "message": "Installed Plugins",
    "description": "Locs.get_Group_Installed"
  },
  "InstallerAvailablePlugins": {
    "message": "Available Plugins",
    "description": "Locs.get_Group_Available"
  },
  "InstallerCategoryAll": {
    "message": "All",
    "description": "Locs.get_Category_All"
  },
  "InstallerInstalledDevPlugins": {
    "message": "Installed Dev Plugins",
    "description": "Locs.get_Category_DevInstalled"
  },
  "InstallerCategoryOther": {
    "message": "Other",
    "description": "Locs.get_Category_Other"
  },
  "InstallerCategoryJobs": {
    "message": "Jobs",
    "description": "Locs.get_Category_Jobs"
  },
  "InstallerCategoryUI": {
    "message": "UI",
    "description": "Locs.get_Category_UI"
  },
  "InstallerCategoryMiniGames": {
    "message": "Mini games",
    "description": "Locs.get_Category_MiniGames"
  },
  "InstallerCategoryInventory": {
    "message": "Inventory",
    "description": "Locs.get_Category_Inventory"
  },
  "InstallerCategorySound": {
    "message": "Sound",
    "description": "Locs.get_Category_Sound"
  },
  "InstallerCategorySocial": {
    "message": "Social",
    "description": "Locs.get_Category_Social"
  },
  "InstallerCategoryUtility": {
    "message": "Utility",
    "description": "Locs.get_Category_Utility"
  },
  "DalamudGamepadModeNotifierText": {
    "message": "Gamepad mode is ON. Press L1+L3 to deactivate, press R3 to toggle PluginInstaller.",
    "description": "GamepadModeNotifierWindow.Draw"
  },
  "InstallerHeader": {
    "message": "Установщик плагинов",
    "description": "Locs.get_WindowTitle"
  },
  "InstallerHeaderTesting": {
    "message": " (TESTING)",
    "description": "Locs.get_WindowTitleMod_Testing"
  },
  "InstallerHint": {
    "message": "Это окно позволяет устанавливать и удалять внутриигровые плагины.\nОни сделаны сторонними разработчиками.",
    "description": "Locs.get_Header_Hint"
  },
  "InstallerSearch": {
    "message": "Поиск",
    "description": "Locs.get_Header_SearchPlaceholder"
  },
  "InstallerAlphabetical": {
    "message": "Alphabetical",
    "description": "Locs.get_SortBy_Alphabetical"
  },
  "InstallerDownloadCount": {
    "message": "Download Count",
    "description": "Locs.get_SortBy_DownloadCounts"
  },
  "InstallerLastUpdate": {
    "message": "Last Update",
    "description": "Locs.get_SortBy_LastUpdate"
  },
  "InstallerNewOrNot": {
    "message": "New or not",
    "description": "Locs.get_SortBy_NewOrNot"
  },
  "InstallerSortBy": {
    "message": "Sort By",
    "description": "Locs.get_SortBy_Label"
  },
  "InstallerLoading": {
    "message": "Загрузка плагинов...",
    "description": "Locs.get_TabBody_LoadingPlugins"
  },
  "InstallerDownloadFailed": {
    "message": "Загрузка не удалась.",
    "description": "Locs.get_TabBody_DownloadFailed"
  },
  "InstallerSafeMode": {
    "message": "Dalamud is running in Plugin Safe Mode, restart to activate plugins.",
    "description": "Locs.get_TabBody_SafeMode"
  },
  "InstallerNoMatching": {
    "message": "No plugins were found matching your search.",
    "description": "Locs.get_TabBody_SearchNoMatching"
  },
  "InstallerNoCompatible": {
    "message": "Совместимые плагины не найдены :( Пожалуйста, перезапустите игру и попробуйте еще раз.",
    "description": "Locs.get_TabBody_SearchNoCompatible"
  },
  "InstallerNoInstalled": {
    "message": "В настоящее время плагины не установлены. Вы можете установить их на вкладке «Доступные плагины».",
    "description": "Locs.get_TabBody_SearchNoInstalled"
  },
  "InstallerInstalled": {
    "message": " (установлено)",
    "description": "Locs.get_PluginTitleMod_Installed"
  },
  "InstallerDisabled": {
    "message": " (отключено)",
    "description": "Locs.get_PluginTitleMod_Disabled"
  },
  "InstallerUnloaded": {
    "message": " (unloaded)",
    "description": "Locs.get_PluginTitleMod_Unloaded"
  },
  "InstallerHasUpdate": {
    "message": " (has update)",
    "description": "Locs.get_PluginTitleMod_HasUpdate"
  },
  "InstallerUpdated": {
    "message": " (обновлено)",
    "description": "Locs.get_PluginTitleMod_Updated"
  },
  "InstallerTestingVersion": {
    "message": " (тестовая версия)",
    "description": "Locs.get_PluginTitleMod_TestingVersion"
  },
  "InstallerUpdateFailed": {
    "message": " (обновление не удалось)",
    "description": "Locs.get_PluginTitleMod_UpdateFailed"
  },
  "InstallerLoadError": {
    "message": " (load error)",
    "description": "Locs.get_PluginTitleMod_LoadError"
  },
  "InstallerUnloadError": {
    "message": " (unload error)",
    "description": "Locs.get_PluginTitleMod_UnloadError"
  },
  "InstallerOutdatedError": {
    "message": " (outdated)",
    "description": "Locs.get_PluginTitleMod_OutdatedError"
  },
  "InstallerBannedError": {
    "message": " (banned)",
    "description": "Locs.get_PluginTitleMod_BannedError"
  },
  "InstallerNewPlugin ": {
    "message": " New!",
    "description": "Locs.get_PluginTitleMod_New"
  },
  "InstallerMarkAllSeen": {
    "message": "Mark all as seen",
    "description": "Locs.get_PluginContext_MarkAllSeen"
  },
  "InstallerHidePlugin": {
    "message": "Hide from installer",
    "description": "Locs.get_PluginContext_HidePlugin"
  },
  "InstallerDeletePluginConfig": {
    "message": "Reset plugin",
    "description": "Locs.get_PluginContext_DeletePluginConfig"
  },
  "InstallerDeletePluginConfigReload": {
    "message": "Reset plugin settings & reload",
    "description": "Locs.get_PluginContext_DeletePluginConfigReload"
  },
  "InstallerAuthorWithoutDownloadCount": {
    "message": " by {0}",
    "description": "Locs.PluginBody_AuthorWithoutDownloadCount"
  },
  "InstallerAuthorWithDownloadCount": {
    "message": " by {0}, {1} downloads",
    "description": "Locs.PluginBody_AuthorWithDownloadCount"
  },
  "InstallerAuthorWithDownloadCountUnavailable": {
    "message": " by {0}, download count unavailable",
    "description": "Locs.PluginBody_AuthorWithDownloadCountUnavailable"
  },
  "InstallerDevPluginPath": {
    "message": "From {0}",
    "description": "Locs.PluginBody_DevPluginPath"
  },
  "InstallerPlugin3rdPartyRepo": {
    "message": "From custom plugin repository {0}",
    "description": "Locs.PluginBody_Plugin3rdPartyRepo"
  },
  "InstallerDevPlugin": {
    "message": " This plugin is available in one of your repos, please remove it from the devPlugins folder.",
    "description": "Locs.get_PluginBody_AvailableDevPlugin"
  },
  "InstallerDeleteDevPlugin ": {
    "message": " To delete this plugin, please remove it from the devPlugins folder.",
    "description": "Locs.get_PluginBody_DeleteDevPlugin"
  },
  "InstallerOutdatedPluginBody ": {
    "message": "This plugin is outdated and incompatible at the moment. Please wait for it to be updated by its author.",
    "description": "Locs.get_PluginBody_Outdated"
  },
  "InstallerBannedPluginBody ": {
    "message": "This plugin version is banned due to incompatibilities and not available at the moment. Please wait for it to be updated by its author.",
    "description": "Locs.get_PluginBody_Banned"
  },
  "InstallerInstall": {
    "message": "Install v{0}",
    "description": "Locs.PluginButton_InstallVersion"
  },
  "InstallerWorking": {
    "message": "Working",
    "description": "Locs.get_PluginButton_Working"
  },
  "InstallerDisable": {
    "message": "Отключить",
    "description": "Locs.get_PluginButton_Disable"
  },
  "InstallerLoad": {
    "message": "Load",
    "description": "Locs.get_PluginButton_Load"
  },
  "InstallerUnload": {
    "message": "Unload",
    "description": "Locs.get_PluginButton_Unload"
  },
  "InstallerOpenConfig": {
    "message": "Открыть конфигурацию",
    "description": "Locs.get_PluginButtonToolTip_OpenConfiguration"
  },
  "InstallerStartOnBoot": {
    "message": "Start on boot",
    "description": "Locs.get_PluginButtonToolTip_StartOnBoot"
  },
  "InstallerAutomaticReloading": {
    "message": "Automatic reloading",
    "description": "Locs.get_PluginButtonToolTip_AutomaticReloading"
  },
  "InstallerDeletePlugin ": {
    "message": "Delete plugin",
    "description": "Locs.get_PluginButtonToolTip_DeletePlugin"
  },
  "InstallerVisitPluginUrl": {
    "message": "Visit plugin URL",
    "description": "Locs.get_PluginButtonToolTip_VisitPluginUrl"
  },
  "InstallerUpdateSingle": {
    "message": "Update to {0}",
    "description": "Locs.PluginButtonToolTip_UpdateSingle"
  },
  "InstallerUnloadFailedTooltip": {
    "message": "Plugin unload failed, please restart your game and try again.",
    "description": "Locs.get_PluginButtonToolTip_UnloadFailed"
  },
  "NotificationsPluginInstalledTitle": {
    "message": "Plugin installed!",
    "description": "Locs.get_Notifications_PluginInstalledTitle"
  },
  "NotificationsPluginInstalled": {
    "message": "'{0}' was successfully installed.",
    "description": "Locs.Notifications_PluginInstalled"
  },
  "NotificationsPluginNotInstalledTitle": {
    "message": "Plugin not installed!",
    "description": "Locs.get_Notifications_PluginNotInstalledTitle"
  },
  "NotificationsPluginNotInstalled": {
    "message": "'{0}' failed to install.",
    "description": "Locs.Notifications_PluginNotInstalled"
  },
  "NotificationsNoUpdatesFoundTitle": {
    "message": "No updates found!",
    "description": "Locs.get_Notifications_NoUpdatesFoundTitle"
  },
  "NotificationsNoUpdatesFound": {
    "message": "No updates were found.",
    "description": "Locs.get_Notifications_NoUpdatesFound"
  },
  "NotificationsUpdatesInstalledTitle": {
    "message": "Updates installed!",
    "description": "Locs.get_Notifications_UpdatesInstalledTitle"
  },
  "NotificationsUpdatesInstalled": {
    "message": "Updates for {0} of your plugins were installed.",
    "description": "Locs.Notifications_UpdatesInstalled"
  },
  "NotificationsPluginDisabledTitle": {
    "message": "Plugin disabled!",
    "description": "Locs.get_Notifications_PluginDisabledTitle"
  },
  "NotificationsPluginDisabled": {
    "message": "'{0}' was disabled.",
    "description": "Locs.Notifications_PluginDisabled"
  },
  "InstallerUpdatePlugins": {
    "message": "Обновить плагины",
    "description": "Locs.get_FooterButton_UpdatePlugins"
  },
  "InstallerInProgress": {
    "message": "Выполняется установка...",
    "description": "Locs.get_FooterButton_InProgress"
  },
  "InstallerNoUpdates": {
    "message": "Обновлений не найдено!",
    "description": "Locs.get_FooterButton_NoUpdates"
  },
  "InstallerUpdateComplete": {
    "message": "{0} плагин(ов) обновлен(о)!",
    "description": "Locs.FooterButton_UpdateComplete"
  },
  "InstallerSettings": {
    "message": "Settings",
    "description": "Locs.get_FooterButton_Settings"
  },
  "InstallerScanDevPlugins": {
    "message": "Scan Dev Plugins",
    "description": "Locs.get_FooterButton_ScanDevPlugins"
  },
  "InstallerClose": {
    "message": "Close",
    "description": "Locs.get_FooterButton_Close"
  },
  "InstallerError": {
    "message": "Installer Error",
    "description": "Locs.get_ErrorModal_Title"
  },
  "InstallerContactAuthor": {
    "message": "Please restart your game and try again. If this error occurs again, please contact the plugin author.",
    "description": "Locs.get_ErrorModal_InstallContactAuthor"
  },
  "InstallerInstallFail": {
    "message": "Failed to install plugin {0}.\n{1}",
    "description": "Locs.ErrorModal_InstallFail"
  },
  "InstallerSingleUpdateFail": {
    "message": "Failed to update plugin {0}.\n{1}",
    "description": "Locs.ErrorModal_SingleUpdateFail"
  },
  "InstallerDeleteConfigFail": {
    "message": "Failed to reset the plugin {0}.\n\nThe plugin may not support this action. You can try deleting the configuration manually while the game is shut down - please see the FAQ.",
    "description": "Locs.ErrorModal_DeleteConfigFail"
  },
  "InstallerEnableFail": {
    "message": "Failed to enable plugin {0}.\n{1}",
    "description": "Locs.ErrorModal_EnableFail"
  },
  "InstallerDisableFail": {
    "message": "Failed to disable plugin {0}.\n{1}",
    "description": "Locs.ErrorModal_DisableFail"
  },
  "InstallerUnloadFail": {
    "message": "Failed to unload plugin {0}.\n{1}",
    "description": "Locs.ErrorModal_UnloadFail"
  },
  "InstallerLoadFail": {
    "message": "Failed to load plugin {0}.\n{1}",
    "description": "Locs.ErrorModal_LoadFail"
  },
  "InstallerDeleteFail": {
    "message": "Failed to delete plugin {0}.\n{1}",
    "description": "Locs.ErrorModal_DeleteFail"
  },
  "InstallerUpdaterFatal": {
    "message": "Failed to update plugins.\nPlease restart your game and try again. If this error occurs again, please complain.",
    "description": "Locs.get_ErrorModal_UpdaterFatal"
  },
  "InstallerUpdaterFail": {
    "message": "Failed to update {0} plugins.\nPlease restart your game and try again. If this error occurs again, please complain.",
    "description": "Locs.ErrorModal_UpdaterFail"
  },
  "InstallerUpdaterFailPartial": {
    "message": "Updated {0} plugins, failed to update {1}.\nPlease restart your game and try again. If this error occurs again, please complain.",
    "description": "Locs.ErrorModal_UpdaterFailPartial"
  },
  "InstallerErrorPluginInfo": {
    "message": "\n\nСледующие плагины вызвали эти проблемы:\n\n{0}\nВы можете попробовать удалить эти плагины вручную и переустановить их.",
    "description": "Locs.ErrorModal_HintBlame"
  },
  "InstallerFeedback": {
    "message": "Send Feedback",
    "description": "Locs.get_FeedbackModal_Title"
  },
  "InstallerFeedbackInfo": {
    "message": "You can send feedback to the developer of \"{0}\" here.\nYou can include your Discord tag or email address if you wish to give them the opportunity to answer.",
    "description": "Locs.FeedbackModal_Text"
  },
  "InstallerFeedbackContactInfo": {
    "message": "Contact information",
    "description": "Locs.get_FeedbackModal_ContactInformation"
  },
  "InstallerFeedbackIncludeLastError": {
    "message": "Include last error message",
    "description": "Locs.get_FeedbackModal_IncludeLastError"
  },
  "InstallerFeedbackIncludeLastErrorHint": {
    "message": "This option can give the plugin developer useful feedback on what exactly went wrong.",
    "description": "Locs.get_FeedbackModal_IncludeLastErrorHint"
  },
  "InstallerFeedbackHint": {
    "message": "All plugin developers will be able to see your feedback.\nPlease never include any personal or revealing information.\nIf you chose to include the last error message, information like your Windows username may be included.\n\nThe collected feedback is not stored on our end and immediately relayed to Discord.",
    "description": "Locs.get_FeedbackModal_Hint"
  },
  "InstallerFeedbackNotificationSuccess": {
    "message": "Your feedback was sent successfully!",
    "description": "Locs.get_FeedbackModal_NotificationSuccess"
  },
  "InstallerFeedbackNotificationError": {
    "message": "Your feedback could not be sent.",
    "description": "Locs.get_FeedbackModal_NotificationError"
  },
  "DalamudPluginUpdates": {
    "message": "Обновления:",
    "description": "Locs.get_PluginUpdateHeader_Chatbox"
  },
  "OK": {
    "message": "ОК",
    "description": "Locs.get_ErrorModalButton_Ok"
  },
  "DalamudSettingsHeader": {
    "message": "Настройки Dalamud",
    "description": "SettingsWindow..ctor"
  },
  "DalamudSettingsGeneral": {
    "message": "Общие",
    "description": "SettingsWindow.Draw"
  },
  "DalamudSettingsVisual": {
    "message": "Внешний вид",
    "description": "SettingsWindow.Draw"
  },
  "DalamudSettingsExperimental": {
    "message": "Экспериментальные",
    "description": "SettingsWindow.Draw"
  },
  "DalamudSettingsLanguage": {
    "message": "Язык",
    "description": "SettingsWindow.DrawGeneralTab"
  },
  "DalamudSettingsLanguageHint": {
    "message": "Выберите язык, на котором будет отображаться Dalamud.",
    "description": "SettingsWindow.DrawGeneralTab"
  },
  "DalamudSettingsChannel": {
    "message": "Общий канал чата",
    "description": "SettingsWindow.DrawGeneralTab"
  },
  "DalamudSettingsChannelHint": {
    "message": "Выберите канал чата, который будет использоваться для общих сообщений Dalamud.",
    "description": "SettingsWindow.DrawGeneralTab"
  },
  "DalamudSettingsFlash": {
    "message": "Мигать окном FFXIV при готовности Duty Finder",
    "description": "SettingsWindow.DrawGeneralTab"
  },
  "DalamudSettingsFlashHint": {
    "message": "Мигать окном FFXIV на панели задач, когда Duty Finder готов.",
    "description": "SettingsWindow.DrawGeneralTab"
  },
  "DalamudSettingsDutyFinderMessage": {
    "message": "Сообщение в журнале чата при готовности Duty Finder",
    "description": "SettingsWindow.DrawGeneralTab"
  },
  "DalamudSettingsDutyFinderMessageHint": {
    "message": "Отправить сообщение в чате FFXIV, когда Duty Finder будет готов.",
    "description": "SettingsWindow.DrawGeneralTab"
  },
  "DalamudSettingsPrintPluginsWelcomeMsg": {
    "message": "Отображать загруженные плагины в приветственном сообщении",
    "description": "SettingsWindow.DrawGeneralTab"
  },
  "DalamudSettingsPrintPluginsWelcomeMsgHint": {
    "message": "Отображать загруженные плагины в чате FFXIV при входе в систему персонажем.",
    "description": "SettingsWindow.DrawGeneralTab"
  },
  "DalamudSettingsAutoUpdatePlugins": {
    "message": "Автообновление плагинов",
    "description": "SettingsWindow.DrawGeneralTab"
  },
  "DalamudSettingsAutoUpdatePluginsMsgHint": {
    "message": "Автоматически обновлять плагины при входе в систему персонажем.",
    "description": "SettingsWindow.DrawGeneralTab"
  },
  "DalamudSettingsSystemMenu": {
    "message": "Dalamud buttons in system menu",
    "description": "SettingsWindow.DrawGeneralTab"
  },
  "DalamudSettingsSystemMenuMsgHint": {
    "message": "Add buttons for Dalamud plugins and settings to the system menu.",
    "description": "SettingsWindow.DrawGeneralTab"
  },
  "DalamudSettingsDisableRmtFiltering": {
    "message": "Disable RMT Filtering",
    "description": "SettingsWindow.DrawGeneralTab"
  },
  "DalamudSettingsDisableRmtFilteringMsgHint": {
    "message": "Disable dalamud's built-in RMT ad filtering.",
    "description": "SettingsWindow.DrawGeneralTab"
  },
  "DalamudSettingsGlobalUiScale": {
    "message": "Общий масштаб пользовательского интерфейса",
    "description": "SettingsWindow.DrawLookAndFeelTab"
  },
  "DalamudSettingsGlobalUiScaleHint": {
    "message": "Масштабировать все элементы пользовательского интерфейса XIVLauncher - полезно для 4K дисплеев.",
    "description": "SettingsWindow.DrawLookAndFeelTab"
  },
  "DalamudSettingsOpenStyleEditor": {
    "message": "Open Style Editor",
    "description": "SettingsWindow.DrawLookAndFeelTab"
  },
  "DalamudSettingsStyleEditorHint": {
    "message": "Modify the look & feel of Dalamud windows.",
    "description": "SettingsWindow.DrawLookAndFeelTab"
  },
  "DalamudSettingToggleUiHideOptOutNote": {
    "message": "Плагины могут самостоятельно отказаться от указанных ниже настроек.",
    "description": "SettingsWindow.DrawLookAndFeelTab"
  },
  "DalamudSettingToggleUiHide": {
    "message": "Скрыть пользовательский интерфейс плагина, когда пользовательский интерфейс игры выключен",
    "description": "SettingsWindow.DrawLookAndFeelTab"
  },
  "DalamudSettingToggleUiHideHint": {
    "message": "Скрыть все окна, открытые с помощью плагинов, при переключении игрового оверлея.",
    "description": "SettingsWindow.DrawLookAndFeelTab"
  },
  "DalamudSettingToggleUiHideDuringCutscenes": {
    "message": "Скрыть пользовательский интерфейс плагина во время кат-сцен",
    "description": "SettingsWindow.DrawLookAndFeelTab"
  },
  "DalamudSettingToggleUiHideDuringCutscenesHint": {
    "message": "Скрыть все окна, открытые плагинами, во время кат-сцен.",
    "description": "SettingsWindow.DrawLookAndFeelTab"
  },
  "DalamudSettingToggleUiHideDuringGpose": {
    "message": "Скрыть пользовательский интерфейс плагина, пока GPose активен",
    "description": "SettingsWindow.DrawLookAndFeelTab"
  },
  "DalamudSettingToggleUiHideDuringGposeHint": {
    "message": "Скрыть все открытые окна плагинами, пока активен GPose.",
    "description": "SettingsWindow.DrawLookAndFeelTab"
  },
  "DalamudSettingToggleFocusManagement": {
    "message": "Use escape to close Dalamud windows",
    "description": "SettingsWindow.DrawLookAndFeelTab"
  },
  "DalamudSettingToggleFocusManagementHint": {
    "message": "This will cause Dalamud windows to behave like in-game windows when pressing escape.\nThey will close one after another until all are closed. May not work for all plugins.",
    "description": "SettingsWindow.DrawLookAndFeelTab"
  },
  "DalamudSettingToggleViewports": {
    "message": "Включить многоэкранный режим",
    "description": "SettingsWindow.DrawLookAndFeelTab"
  },
  "DalamudSettingToggleViewportsHint": {
    "message": "Это позволит вам перемещать окна плагинов на другие мониторы.\nБудет работать только в оконном или оконном режиме без полей.",
    "description": "SettingsWindow.DrawLookAndFeelTab"
  },
  "DalamudSettingToggleDocking": {
    "message": "Включить стыковку окон",
    "description": "SettingsWindow.DrawLookAndFeelTab"
  },
  "DalamudSettingToggleDockingHint": {
    "message": "Это позволит вам объединять и вкладывать окна плагинов.",
    "description": "SettingsWindow.DrawLookAndFeelTab"
  },
  "DalamudSettingToggleGamepadNavigation": {
    "message": "Control plugins via gamepad",
    "description": "SettingsWindow.DrawLookAndFeelTab"
  },
  "DalamudSettingToggleGamepadNavigationHint": {
    "message": "This will allow you to toggle between game and plugin navigation via L1+L3.\nToggle the PluginInstaller window via R3 if ImGui navigation is enabled.",
    "description": "SettingsWindow.DrawLookAndFeelTab"
  },
  "DalamudSettingsPluginTest": {
    "message": "Получить тестовые сборки плагинов",
    "description": "SettingsWindow.DrawExperimentalTab"
  },
  "DalamudSettingsPluginTestHint": {
    "message": "Получить предварительные версии тестирования для плагинов.",
    "description": "SettingsWindow.DrawExperimentalTab"
  },
  "DalamudSettingsPluginTestWarning": {
    "message": "Тестовые плагины, возможно, не были проверены до публикации. Пожалуйста, включите это только в том случае, если вы осознаете риски.",
    "description": "SettingsWindow.DrawExperimentalTab"
  },
  "DalamudSettingsClearHidden": {
    "message": "Очистить скрытые плагины",
    "description": "SettingsWindow.DrawExperimentalTab"
  },
  "DalamudSettingsClearHiddenHint": {
    "message": "Восстановить плагины, которые вы ранее скрыли от установщика плагинов.",
    "description": "SettingsWindow.DrawExperimentalTab"
  },
  "DalamudSettingsCustomRepo": {
    "message": "Пользовательские репозитории плагинов",
    "description": "SettingsWindow.DrawCustomReposSection"
  },
  "DalamudSettingsChanged": {
    "message": "(Changed)",
    "description": "SettingsWindow.DrawCustomReposSection"
  },
  "DalamudSettingCustomRepoHint": {
    "message": "Добавить пользовательские репозитории плагинов.",
    "description": "SettingsWindow.DrawCustomReposSection"
  },
  "DalamudSettingCustomRepoWarning": {
    "message": "Мы не несем никакой ответственности за сторонние плагины и репозитории.\nБудьте осторожны при установке сторонних плагинов из ненадежных источников.",
    "description": "SettingsWindow.DrawCustomReposSection"
  },
  "DalamudThirdRepoExists": {
    "message": "Репозиторий уже существует.",
    "description": "SettingsWindow.DrawCustomReposSection"
  },
  "DalamudSettingsDevPluginLocation": {
    "message": "Dev Plugin Locations",
    "description": "SettingsWindow.DrawDevPluginLocationsSection"
  },
  "DalamudSettingsDevPluginLocationsHint": {
    "message": "Add additional dev plugin load locations.\nThese can be either the directory or DLL path.",
    "description": "SettingsWindow.DrawDevPluginLocationsSection"
  },
  "DalamudDevPluginLocationExists": {
    "message": "Location already exists.",
    "description": "SettingsWindow.DrawDevPluginLocationsSection"
  },
  "Save": {
    "message": "Сохранить",
    "description": "SettingsWindow.DrawSaveCloseButtons"
  },
  "Close": {
    "message": "Close",
    "description": "SettingsWindow.DrawSaveCloseButtons"
  },
  "SaveAndClose": {
    "message": "Сохранить и закрыть",
    "description": "SettingsWindow.DrawSaveCloseButtons"
  },
  "RenameStyleModalTitle": {
    "message": "Rename Style",
    "description": "StyleEditorWindow.Draw"
  },
  "StyleEditorChooseStyle": {
    "message": "Choose Style:",
    "description": "StyleEditorWindow.Draw"
  },
  "StyleEditorAddNew": {
    "message": "Add new style",
    "description": "StyleEditorWindow.Draw"
  },
  "StyleEditorDeleteStyle": {
    "message": "Delete current style",
    "description": "StyleEditorWindow.Draw"
  },
  "StyleEditorRenameStyle": {
    "message": "Rename style",
    "description": "StyleEditorWindow.Draw"
  },
  "StyleEditorCopy": {
    "message": "Copy style to clipboard for sharing",
    "description": "StyleEditorWindow.Draw"
  },
  "StyleEditorImport": {
    "message": "Import style from clipboard",
    "description": "StyleEditorWindow.Draw"
  },
  "StyleEditorNotAllowed": {
    "message": "You cannot edit built-in styles. Please add a new style first.",
    "description": "StyleEditorWindow.Draw"
  },
  "StyleEditorApplying": {
    "message": "Applying style...",
    "description": "StyleEditorWindow.Draw"
  },
  "StyleEditorVariables": {
    "message": "Variables",
    "description": "StyleEditorWindow.Draw"
  },
  "StyleEditorColors": {
    "message": "Colors",
    "description": "StyleEditorWindow.Draw"
  },
  "StyleEditorEnterName": {
    "message": "Please enter the new name for this style.",
    "description": "StyleEditorWindow.Draw"
  },
  "DalamudWelcome": {
    "message": "Dalamud vD{0} загружен.",
    "description": "ChatHandlers.PrintWelcomeMessage"
  },
  "PluginsWelcome": {
    "message": " {0} плагин(ов) загружен(о).",
    "description": "ChatHandlers.PrintWelcomeMessage"
  },
  "DalamudPluginLoaded": {
    "message": "    》 {0} v{1} загружен.",
    "description": "ChatHandlers.PrintWelcomeMessage"
  },
  "DalamudUpdated": {
    "message": "Внутриигровое дополнение обновлено или успешно переустановлено! Пожалуйста, проверьте Discord, чтобы увидеть полный список изменений.",
    "description": "ChatHandlers.PrintWelcomeMessage"
  },
  "DalamudPluginUpdateCheckFail": {
    "message": "Не удалось проверить наличие обновлений плагина.",
    "description": "<>c__DisplayClass16_0.<AutoUpdatePlugins>b__1"
  },
  "DalamudPluginAutoUpdate": {
    "message": "Автоматическое обновление:",
    "description": "<>c__DisplayClass16_0.<AutoUpdatePlugins>b__1"
  },
  "NotificationUpdatedPlugins": {
    "message": "{0} of your plugins were updated.",
    "description": "<>c__DisplayClass16_0.<AutoUpdatePlugins>b__1"
  },
  "NotificationAutoUpdate": {
    "message": "Auto-Update",
    "description": "<>c__DisplayClass16_0.<AutoUpdatePlugins>b__1"
  },
  "DalamudPluginUpdateRequired": {
    "message": "Необходимо обновить один или несколько ваших плагинов. Пожалуйста, используйте команду /xlplugins в игре, чтобы обновить их!",
    "description": "<>c__DisplayClass16_0.<AutoUpdatePlugins>b__1"
  },
  "SystemMenuPlugins": {
    "message": "Плагины Dalamud",
    "description": "DalamudAtkTweaks.AgentHudOpenSystemMenuDetour"
  },
  "SystemMenuSettings": {
    "message": "Настройки Dalamud",
    "description": "DalamudAtkTweaks.AgentHudOpenSystemMenuDetour"
  }
}